baba/__init__.py
baba/taskbase.py
baba/test.py
baba-0.1.8.dist-info/LICENSE.txt
baba-0.1.8.dist-info/METADATA
baba-0.1.8.dist-info/WHEEL
baba-0.1.8.dist-info/top_level.txt
baba-0.1.8.dist-info/RECORD
