Metadata-Version: 2.1
Name: baba
Version: 0.1.8
Summary: 好爸爸的每个类都是被用来继承的。作为顶层设计，它为通用行为实现了最基础的标准实践。比如自动埋点、权限控制、性能分析、任务流转、异常处理、单元测试等。
Home-page: https://pypi.org/project/baba/
Author: jie.kim
Author-email: ubbs@163.com
License: Apache
License-File: LICENSE.txt
